pygeo/__init__.py
pygeo/__main__.py
pygeo/main.py
pygeogis-0.0.1.dist-info/METADATA
pygeogis-0.0.1.dist-info/WHEEL
pygeogis-0.0.1.dist-info/entry_points.txt
pygeogis-0.0.1.dist-info/top_level.txt
pygeogis-0.0.1.dist-info/RECORD
