Metadata-Version: 2.1
Name: pygeogis
Version: 0.0.1
Home-page: 
Author: Lawrence Kimutai
Maintainer: Lawrence Kimutai
Maintainer-email: lawrencekimutai09@gmail.com
Classifier: License :: OSI Approved :: MIT License
Classifier: Intended Audience :: Science/Research
Classifier: Programming Language :: Python :: 3.11
Requires-Dist: rasterio (==1.3.6)
